setup.py
bin/fcg
bin/fcg-easy
flashcachegroup.egg-info/PKG-INFO
flashcachegroup.egg-info/SOURCES.txt
flashcachegroup.egg-info/dependency_links.txt
flashcachegroup.egg-info/top_level.txt
libfcg/__init__.py
libfcg/fcg.py
libfcg/flashcache.py
libfcg/utils.py
libfcg/common/__init__.py
libfcg/common/chain.py
libfcg/common/executor.py
libfcg/common/processutils.py