Metadata-Version: 1.0
Name: flashcachegroup
Version: 0.6.6
Summary: create cache for a group of disks
Home-page: https://github.com/lihuiba/flashcachegroup
Author: Ziyang Li
Author-email: anzigly@gmail.com
License: GPL
Keywords: flashcache group
Platform: UNKNOWN
